LICENSE
MANIFEST.in
README.md
setup.cfg
setup.py
tap_gemini/__init__.py
tap_gemini/api.py
tap_gemini/exceptions.py
tap_gemini/report.py
tap_gemini/settings.py
tap_gemini/transport.py
tap_gemini.egg-info/PKG-INFO
tap_gemini.egg-info/SOURCES.txt
tap_gemini.egg-info/dependency_links.txt
tap_gemini.egg-info/entry_points.txt
tap_gemini.egg-info/requires.txt
tap_gemini.egg-info/top_level.txt
tap_gemini/metadata/ad_extension_details.json
tap_gemini/metadata/adjustment_stats.json
tap_gemini/metadata/advertiser.json
tap_gemini/metadata/call_extension_stats.json
tap_gemini/metadata/campaign.json
tap_gemini/metadata/campaign_bid_performance_stats.json
tap_gemini/metadata/conversion_rules_stats.json
tap_gemini/metadata/domain_performance_stats.json
tap_gemini/metadata/keyword_stats.json
tap_gemini/metadata/performance_stats.json
tap_gemini/metadata/product_ad_performance_stats.json
tap_gemini/metadata/product_ads.json
tap_gemini/metadata/search_stats.json
tap_gemini/metadata/site_performance_stats.json
tap_gemini/metadata/slot_performance_stats.json
tap_gemini/metadata/user_stats.json
tap_gemini/schemas/ad_extension_details.json
tap_gemini/schemas/adjustment_stats.json
tap_gemini/schemas/advertiser.json
tap_gemini/schemas/call_extension_stats.json
tap_gemini/schemas/campaign.json
tap_gemini/schemas/campaign_bid_performance_stats.json
tap_gemini/schemas/conversion_rules_stats.json
tap_gemini/schemas/domain_performance_stats.json
tap_gemini/schemas/keyword_stats.json
tap_gemini/schemas/performance_stats.json
tap_gemini/schemas/product_ad_performance_stats.json
tap_gemini/schemas/product_ads.json
tap_gemini/schemas/search_stats.json
tap_gemini/schemas/site_performance_stats.json
tap_gemini/schemas/slot_performance_stats.json
tap_gemini/schemas/user_stats.json