Metadata-Version: 1.1
Name: tap-gemini
Version: 0.1.2
Summary: Singer.io tap for extracting data from Yahoo Gemini
Home-page: https://github.com/singer-io/tap-gemini
Author: Joe Heffer
Author-email: UNKNOWN
License: UNKNOWN
Platform: UNKNOWN
Classifier: Programming Language :: Python :: 3 :: Only
